README.rst
setup.py
django_mapshop.egg-info/PKG-INFO
django_mapshop.egg-info/SOURCES.txt
django_mapshop.egg-info/dependency_links.txt
django_mapshop.egg-info/not-zip-safe
django_mapshop.egg-info/top_level.txt
mapshop/__init__.py
mapshop/admin.py
mapshop/ajax.py
mapshop/api.py
mapshop/forms.py
mapshop/models.py
mapshop/settings.py
mapshop/tasks.py
mapshop/tests.py
mapshop/urls.py
mapshop/views.py
mapshop/management/__init__.py
mapshop/management/commands/__init__.py
mapshop/management/commands/load_data.py
mapshop/management/commands/load_kiosk.py
mapshop/management/commands/load_products.py
mapshop/management/commands/test_api.py
mapshop/management/commands/utils.py
mapshop/migrations/0001_initial.py
mapshop/migrations/0002_auto__add_preorder__add_field_client_treatment__add_field_client_surna.py
mapshop/migrations/0003_auto__chg_field_order_kiosk.py
mapshop/migrations/0004_auto__add_field_product_rate.py
mapshop/migrations/0005_auto__add_category__add_field_product_category.py
mapshop/migrations/0006_auto__del_field_product_available.py
mapshop/migrations/0007_auto__add_field_product_available.py
mapshop/migrations/0008_auto__add_field_productimages_cropping.py
mapshop/migrations/0009_auto__add_field_kiosk_name.py
mapshop/migrations/0009_auto__chg_field_client_account_org__chg_field_client_postal_index_org_.py
mapshop/migrations/0010_auto__del_field_kiosk_foto__del_field_kiosk_address.py
mapshop/migrations/0011_auto__add_field_kiosk_address__add_field_kiosk_foto.py
mapshop/migrations/0012_auto__del_field_kiosk_foto.py
mapshop/migrations/0013_auto__add_field_kiosk_foto.py
mapshop/migrations/0014_auto__del_field_kiosk_foto.py
mapshop/migrations/0015_auto__add_field_kiosk_foto.py
mapshop/migrations/0016_auto__del_field_kiosk_foto.py
mapshop/migrations/0017_auto__add_field_kiosk_foto.py
mapshop/migrations/0018_auto__add_field_kiosk_scheduler__chg_field_client_account_org__chg_fie.py
mapshop/migrations/0019_auto__add_field_order_session.py
mapshop/migrations/0020_auto__chg_field_order_client__chg_field_order_session.py
mapshop/migrations/0021_auto__add_field_client_user_id__add_field_product_name_slug.py
