Metadata-Version: 1.0
Name: django-mapshop
Version: 0.3
Summary: Internet shop with geographic points
Home-page: http://github.com/storborg/funniest
Author: Dmitry Zharikov
Author-email: zdimon77@gmail.com
License: MIT
Platform: UNKNOWN
